SteamMarket/__init__.py
SteamMarket/steam_market.py
steam_market_price-0.0.1.dist-info/LICENSE
steam_market_price-0.0.1.dist-info/METADATA
steam_market_price-0.0.1.dist-info/WHEEL
steam_market_price-0.0.1.dist-info/top_level.txt
steam_market_price-0.0.1.dist-info/RECORD
