Metadata-Version: 2.1
Name: steam-market-price
Version: 0.0.1
Summary: Package to get prices for steam items
Home-page: https://github.com/NavesSapnis/SteamMarket
Author: Veih
Author-email: veih.work@gmail.com
Classifier: Programming Language :: Python :: 3
Classifier: License :: OSI Approved :: MIT License
Classifier: Operating System :: OS Independent
Requires-Python: >=3.9
License-File: LICENSE
